gs/__init__.py
gs/cache/__init__.py
gs/cache/cache_protocol.py
gs/cache/file_cache.py
gs/cache/memory_cache.py
gs/cache/redis_cache.py
gs/config/__init__.py
gs/config/base_config.py
gs/config/class_properties.py
gs/dotenv/__init__.py
gs/dotenv/load_dotenv.py
py_gstools-0.2.1.dist-info/LICENSE
py_gstools-0.2.1.dist-info/METADATA
py_gstools-0.2.1.dist-info/WHEEL
py_gstools-0.2.1.dist-info/top_level.txt
py_gstools-0.2.1.dist-info/zip-safe
py_gstools-0.2.1.dist-info/RECORD
