Metadata-Version: 2.1
Name: py-gstools
Version: 0.2.1
Summary: Tool classes and functions for Guiosoft projects
Home-page: https://github.com/guionardo/py-gstools
Author: Guionardo Furlan
Author-email: guionardo@gmail.com
License: MIT
Project-URL: Documentation, https://github.com/guionardo/py-gstools/wiki
Project-URL: Source, https://github.com/guionardo/py-gstools
Keywords: tools
Classifier: Development Status :: 4 - Beta
Classifier: Environment :: Console
Classifier: Operating System :: OS Independent
Classifier: Intended Audience :: Developers
Classifier: License :: OSI Approved :: MIT License
Classifier: Topic :: Software Development :: Build Tools
Classifier: Topic :: Utilities
Classifier: Programming Language :: Python
Classifier: Programming Language :: Python :: 3.8
Classifier: Programming Language :: Python :: 3.9
Classifier: Programming Language :: Python :: 3.10
Requires-Python: >=3.8.*
License-File: LICENSE
Requires-Dist: redis (>=4.3.3)
Requires-Dist: PyYAML (==6.0)
